nonebot_plugin_starrail_calendar/__init__.py
nonebot_plugin_starrail_calendar/browser.py
nonebot_plugin_starrail_calendar/config.py
nonebot_plugin_starrail_calendar/data_source.py
nonebot_plugin_starrail_calendar/draw_calendar.py
nonebot_plugin_starrail_calendar/template/calendar.html
nonebot_plugin_starrail_calendar/template/index.css
nonebot_plugin_starrail_calendar/template/iview.css
nonebot_plugin_starrail_calendar/template/normalize.css
nonebot_plugin_starrail_calendar/utils.py
nonebot_plugin_starrail_calendar-1.0.8.dist-info/LICENSE
nonebot_plugin_starrail_calendar-1.0.8.dist-info/METADATA
nonebot_plugin_starrail_calendar-1.0.8.dist-info/WHEEL
nonebot_plugin_starrail_calendar-1.0.8.dist-info/RECORD
