Metadata-Version: 2.1
Name: nonebot-plugin-starrail-calendar
Version: 1.0.8
Summary: 查看《崩坏：星穹铁道》官方活动
Author: nicklly
Author-email: 1134741727@qq.com
Requires-Python: >=3.10,<4.0
Classifier: Programming Language :: Python :: 3
Classifier: Programming Language :: Python :: 3.10
Classifier: Programming Language :: Python :: 3.11
Requires-Dist: apscheduler (>=3.10.1,<3.11.0)
Requires-Dist: httpx (>=0.23.3,<0.24.0)
Requires-Dist: jinja2 (>=3.1.2,<4.0.0)
Requires-Dist: nonebot-adapter-onebot (>=2.2.2,<3.0.0)
Requires-Dist: nonebot2 (>=2.0.0,<3.0.0)
Requires-Dist: playwright (>=1.32.1,<2.0.0)
